daaskit/__init__.py
daaskit/sdk/__init__.py
daaskit/sdk/apis.py
daaskit/sdk/config.py
daaskit/sdk/log.py
daaskit/sdk/mq.py
daaskit/sdk/sql.py
daaskit/sdk/sqlhelper.py
daaskit/sdk/sqlplus.py
daaskit/sdk/tsdb.py
daaskit/sdk/util.py
daaskit/sdk/api_modules/__init__.py
daaskit/sdk/api_modules/ext_api/__init__.py
daaskit/sdk/api_modules/ext_api/ext_api.py
daaskit/sdk/api_modules/system/__init__.py
daaskit/sdk/api_modules/system/user.py
daaskit/sdk/utils/__init__.py
daaskit/sdk/utils/request.py
daaskit/sdk/utils/time.py
daaskit-0.0.17.dist-info/licenses/LICENSE
tests/__init__.py
tests/db_test.py
daaskit-0.0.17.dist-info/METADATA
daaskit-0.0.17.dist-info/WHEEL
daaskit-0.0.17.dist-info/top_level.txt
daaskit-0.0.17.dist-info/RECORD
