Metadata-Version: 2.4
Name: daaskit
Version: 0.0.17
Summary: python sdk for platform
Author: zhangjq
Author-email: zhangjq@qianqiusoft.com
Classifier: Programming Language :: Python :: 3
Classifier: License :: OSI Approved :: MIT License
Classifier: Operating System :: OS Independent
Requires-Python: >=3
License-File: LICENSE
Requires-Dist: pymysql
Requires-Dist: nats-py
Requires-Dist: influxdb
Requires-Dist: influxdb-client
Requires-Dist: DBUtils
Requires-Dist: cryptography
Dynamic: author
Dynamic: author-email
Dynamic: classifier
Dynamic: description
Dynamic: description-content-type
Dynamic: license-file
Dynamic: requires-dist
Dynamic: requires-python
Dynamic: summary
